.gitignore
MANIFEST.in
README.rst
setup.py
python_pragmatic/__init__.py
python_pragmatic/classes.py
python_pragmatic/dates.py
python_pragmatic/environment.py
python_pragmatic/os.py
python_pragmatic/strings.py
python_pragmatic/thirdparty.py
python_pragmatic.egg-info/PKG-INFO
python_pragmatic.egg-info/SOURCES.txt
python_pragmatic.egg-info/dependency_links.txt
python_pragmatic.egg-info/top_level.txt