Metadata-Version: 2.1
Name: python-pragmatic
Version: 1.0.0
Summary: Pragmatic tools and utilities for Python projects
Home-page: https://github.com/PragmaticMates/python-pragmatic
Author: Pragmatic Mates
Author-email: info@pragmaticmates.com
Maintainer: Pragmatic Mates
Maintainer-email: info@pragmaticmates.com
License: BSD License
Keywords: pragmatic tools utils
Platform: UNKNOWN
Classifier: Programming Language :: Python
Classifier: Programming Language :: Python :: 2.5
Classifier: Programming Language :: Python :: 2.6
Classifier: Programming Language :: Python :: 2.7
Classifier: Operating System :: OS Independent
Classifier: Intended Audience :: Developers
Classifier: License :: OSI Approved :: BSD License
Classifier: Development Status :: 3 - Alpha
